CHANGELOG.md
README.md
docs/changelog.md
docs/commands.md
docs/index.md
moin2gitwiki/__init__.py
moin2gitwiki/cli.py
moin2gitwiki/context.py
moin2gitwiki/fetch_cache.py
moin2gitwiki/gitrevision.py
moin2gitwiki/moin2markdown.py
moin2gitwiki/users.py
moin2gitwiki/wikiindex.py
tests/__init__.py
tests/test_command_line.py
tests/test_version.py
moin2gitwiki-0.8.0.dist-info/LICENSE.md
moin2gitwiki-0.8.0.dist-info/WHEEL
moin2gitwiki-0.8.0.dist-info/entry_points.txt
moin2gitwiki-0.8.0.dist-info/METADATA
moin2gitwiki-0.8.0.dist-info/RECORD
