Metadata-Version: 2.1
Name: moin2gitwiki
Version: 0.8.0
Summary: MoinMoin To Git (Markdown) Wiki Converter
Home-page: https://github.com/nigelm/moin2gitwiki
License: MIT
Author: Nigel Metheringham
Author-email: nigelm@cpan.org
Requires-Python: >=3.8,<4.0
Classifier: License :: OSI Approved :: MIT License
Classifier: Programming Language :: Python :: 3
Classifier: Programming Language :: Python :: 3.8
Classifier: Programming Language :: Python :: 3.9
Classifier: Programming Language :: Python :: 3.10
Classifier: Programming Language :: Python :: 3.11
Requires-Dist: attrs (>=20.3.0,<21.0.0)
Requires-Dist: beautifulsoup4 (>=4.9.3,<5.0.0)
Requires-Dist: click (>=7.1.2,<8.0.0)
Requires-Dist: furl (>=2.1.0,<3.0.0)
Requires-Dist: requests[socks] (>=2.25.1,<3.0.0)
Project-URL: Documentation, https://nigelm.github.io/moin2gitwiki/
Project-URL: Repository, https://github.com/nigelm/moin2gitwiki
